[
{"filename": "1011924.jpg","full": "https://jvr.nyc3.cdn.digitaloceanspaces.com/images/mom/1011924.jpg", "width": "3072", "height": "2048", "aspectRatio": "0.6666666666666666", "src": "https://jvr.nyc3.cdn.digitaloceanspaces.com/images/mom/thumbs/1011924.jpg"},
{"filename": "1011929.jpg","full": "https://jvr.nyc3.cdn.digitaloceanspaces.com/images/mom/1011929.jpg", "width": "3072", "height": "2048", "aspectRatio": "0.6666666666666666", "src": "https://jvr.nyc3.cdn.digitaloceanspaces.com/images/mom/thumbs/1011929.jpg"},
{"filename": "1011942.jpg","full": "https://jvr.nyc3.cdn.digitaloceanspaces.com/images/mom/1011942.jpg", "width": "1884", "height": "1252", "aspectRatio": "0.6645435244161358", "src": "https://jvr.nyc3.cdn.digitaloceanspaces.com/images/mom/thumbs/1011942.jpg"},
{"filename": "2012-09-15 19.32.54-2.jpg","full": "https://jvr.nyc3.cdn.digitaloceanspaces.com/images/mom/2012-09-15 19.32.54-2.jpg", "width": "1225", "height": "1224", "aspectRatio": "0.9991836734693877", "src": "https://jvr.nyc3.cdn.digitaloceanspaces.com/images/mom/thumbs/2012-09-15 19.32.54-2.jpg"},
{"filename": "2016-07-29 21.54.39.jpg","full": "https://jvr.nyc3.cdn.digitaloceanspaces.com/images/mom/2016-07-29 21.54.39.jpg", "width": "5248", "height": "2952", "aspectRatio": "0.5625", "src": "https://jvr.nyc3.cdn.digitaloceanspaces.com/images/mom/thumbs/2016-07-29 21.54.39.jpg"},
{"filename": "2016-07-31 03.28.49.jpg","full": "https://jvr.nyc3.cdn.digitaloceanspaces.com/images/mom/2016-07-31 03.28.49.jpg", "width": "720", "height": "960", "aspectRatio": "1.3333333333333333", "src": "https://jvr.nyc3.cdn.digitaloceanspaces.com/images/mom/thumbs/2016-07-31 03.28.49.jpg"},
{"filename": "203.JPG","full": "https://jvr.nyc3.cdn.digitaloceanspaces.com/images/mom/203.JPG", "width": "4000", "height": "3000", "aspectRatio": "0.75", "src": "https://jvr.nyc3.cdn.digitaloceanspaces.com/images/mom/thumbs/203.jpg"},
{"filename": "205.JPG","full": "https://jvr.nyc3.cdn.digitaloceanspaces.com/images/mom/205.JPG", "width": "4000", "height": "3000", "aspectRatio": "0.75", "src": "https://jvr.nyc3.cdn.digitaloceanspaces.com/images/mom/thumbs/205.jpg"},
{"filename": "3621F80C-E1D6-4955-989D-F62262D10DA8.JPG","full": "https://jvr.nyc3.cdn.digitaloceanspaces.com/images/mom/3621F80C-E1D6-4955-989D-F62262D10DA8.JPG", "width": "1440", "height": "1795", "aspectRatio": "1.2465277777777777", "src": "https://jvr.nyc3.cdn.digitaloceanspaces.com/images/mom/thumbs/3621F80C-E1D6-4955-989D-F62262D10DA8.jpg"},
{"filename": "6650FAB5-A536-4613-9FAA-C4C408EEB90A.JPG","full": "https://jvr.nyc3.cdn.digitaloceanspaces.com/images/mom/6650FAB5-A536-4613-9FAA-C4C408EEB90A.JPG", "width": "1440", "height": "1795", "aspectRatio": "1.2465277777777777", "src": "https://jvr.nyc3.cdn.digitaloceanspaces.com/images/mom/thumbs/6650FAB5-A536-4613-9FAA-C4C408EEB90A.jpg"},
{"filename": "Attachment.JPEG","full": "https://jvr.nyc3.cdn.digitaloceanspaces.com/images/mom/Attachment.JPEG", "width": "2213", "height": "1660", "aspectRatio": "0.7501129688206055", "src": "https://jvr.nyc3.cdn.digitaloceanspaces.com/images/mom/thumbs/Attachment.jpg"},
{"filename": "CFE2169E-2F75-4418-ACCB-87CFA19D5FB5.JPG","full": "https://jvr.nyc3.cdn.digitaloceanspaces.com/images/mom/CFE2169E-2F75-4418-ACCB-87CFA19D5FB5.JPG", "width": "1881", "height": "1881", "aspectRatio": "1", "src": "https://jvr.nyc3.cdn.digitaloceanspaces.com/images/mom/thumbs/CFE2169E-2F75-4418-ACCB-87CFA19D5FB5.jpg"},
{"filename": "DSC00377.JPG","full": "https://jvr.nyc3.cdn.digitaloceanspaces.com/images/mom/DSC00377.JPG", "width": "3072", "height": "2304", "aspectRatio": "0.75", "src": "https://jvr.nyc3.cdn.digitaloceanspaces.com/images/mom/thumbs/DSC00377.jpg"},
{"filename": "DSC00479.JPG","full": "https://jvr.nyc3.cdn.digitaloceanspaces.com/images/mom/DSC00479.JPG", "width": "3072", "height": "2304", "aspectRatio": "0.75", "src": "https://jvr.nyc3.cdn.digitaloceanspaces.com/images/mom/thumbs/DSC00479.jpg"},
{"filename": "DSC00488.JPG","full": "https://jvr.nyc3.cdn.digitaloceanspaces.com/images/mom/DSC00488.JPG", "width": "3072", "height": "2304", "aspectRatio": "0.75", "src": "https://jvr.nyc3.cdn.digitaloceanspaces.com/images/mom/thumbs/DSC00488.jpg"},
{"filename": "DSCF0010.JPG","full": "https://jvr.nyc3.cdn.digitaloceanspaces.com/images/mom/DSCF0010.JPG", "width": "1280", "height": "960", "aspectRatio": "0.75", "src": "https://jvr.nyc3.cdn.digitaloceanspaces.com/images/mom/thumbs/DSCF0010.jpg"},
{"filename": "Easter-1986.jpg","full": "https://jvr.nyc3.cdn.digitaloceanspaces.com/images/mom/Easter-1986.jpg", "width": "1484", "height": "1006", "aspectRatio": "0.6778975741239892", "src": "https://jvr.nyc3.cdn.digitaloceanspaces.com/images/mom/thumbs/Easter-1986.jpg"},
{"filename": "IMG_0001.JPG","full": "https://jvr.nyc3.cdn.digitaloceanspaces.com/images/mom/IMG_0001.JPG", "width": "3264", "height": "2448", "aspectRatio": "0.75", "src": "https://jvr.nyc3.cdn.digitaloceanspaces.com/images/mom/thumbs/IMG_0001.jpg"},
{"filename": "IMG_0003.JPG","full": "https://jvr.nyc3.cdn.digitaloceanspaces.com/images/mom/IMG_0003.JPG", "width": "3264", "height": "2448", "aspectRatio": "0.75", "src": "https://jvr.nyc3.cdn.digitaloceanspaces.com/images/mom/thumbs/IMG_0003.jpg"},
{"filename": "IMG_0014.jpg","full": "https://jvr.nyc3.cdn.digitaloceanspaces.com/images/mom/IMG_0014.jpg", "width": "4032", "height": "3024", "aspectRatio": "0.75", "src": "https://jvr.nyc3.cdn.digitaloceanspaces.com/images/mom/thumbs/IMG_0014.jpg"},
{"filename": "IMG_0034.jpg","full": "https://jvr.nyc3.cdn.digitaloceanspaces.com/images/mom/IMG_0034.jpg", "width": "4032", "height": "3024", "aspectRatio": "0.75", "src": "https://jvr.nyc3.cdn.digitaloceanspaces.com/images/mom/thumbs/IMG_0034.jpg"},
{"filename": "IMG_0075.jpg","full": "https://jvr.nyc3.cdn.digitaloceanspaces.com/images/mom/IMG_0075.jpg", "width": "4032", "height": "3024", "aspectRatio": "0.75", "src": "https://jvr.nyc3.cdn.digitaloceanspaces.com/images/mom/thumbs/IMG_0075.jpg"},
{"filename": "IMG_0082.JPG","full": "https://jvr.nyc3.cdn.digitaloceanspaces.com/images/mom/IMG_0082.JPG", "width": "3264", "height": "2448", "aspectRatio": "0.75", "src": "https://jvr.nyc3.cdn.digitaloceanspaces.com/images/mom/thumbs/IMG_0082.jpg"},
{"filename": "IMG_0095.jpg","full": "https://jvr.nyc3.cdn.digitaloceanspaces.com/images/mom/IMG_0095.jpg", "width": "3024", "height": "3024", "aspectRatio": "1", "src": "https://jvr.nyc3.cdn.digitaloceanspaces.com/images/mom/thumbs/IMG_0095.jpg"},
{"filename": "IMG_0140.jpg","full": "https://jvr.nyc3.cdn.digitaloceanspaces.com/images/mom/IMG_0140.jpg", "width": "4032", "height": "3024", "aspectRatio": "0.75", "src": "https://jvr.nyc3.cdn.digitaloceanspaces.com/images/mom/thumbs/IMG_0140.jpg"},
{"filename": "IMG_0184.jpg","full": "https://jvr.nyc3.cdn.digitaloceanspaces.com/images/mom/IMG_0184.jpg", "width": "3024", "height": "4032", "aspectRatio": "1.3333333333333333", "src": "https://jvr.nyc3.cdn.digitaloceanspaces.com/images/mom/thumbs/IMG_0184.jpg"},
{"filename": "IMG_0214.jpg","full": "https://jvr.nyc3.cdn.digitaloceanspaces.com/images/mom/IMG_0214.jpg", "width": "3024", "height": "4032", "aspectRatio": "1.3333333333333333", "src": "https://jvr.nyc3.cdn.digitaloceanspaces.com/images/mom/thumbs/IMG_0214.jpg"},
{"filename": "IMG_0610.jpg","full": "https://jvr.nyc3.cdn.digitaloceanspaces.com/images/mom/IMG_0610.jpg", "width": "3024", "height": "4032", "aspectRatio": "1.3333333333333333", "src": "https://jvr.nyc3.cdn.digitaloceanspaces.com/images/mom/thumbs/IMG_0610.jpg"},
{"filename": "IMG_0613.JPG","full": "https://jvr.nyc3.cdn.digitaloceanspaces.com/images/mom/IMG_0613.JPG", "width": "2205", "height": "2205", "aspectRatio": "1", "src": "https://jvr.nyc3.cdn.digitaloceanspaces.com/images/mom/thumbs/IMG_0613.jpg"},
{"filename": "IMG_0732 copy.jpg","full": "https://jvr.nyc3.cdn.digitaloceanspaces.com/images/mom/IMG_0732 copy.jpg", "width": "1536", "height": "2048", "aspectRatio": "1.3333333333333333", "src": "https://jvr.nyc3.cdn.digitaloceanspaces.com/images/mom/thumbs/IMG_0732 copy.jpg"},
{"filename": "IMG_0733.jpg","full": "https://jvr.nyc3.cdn.digitaloceanspaces.com/images/mom/IMG_0733.jpg", "width": "3024", "height": "4032", "aspectRatio": "1.3333333333333333", "src": "https://jvr.nyc3.cdn.digitaloceanspaces.com/images/mom/thumbs/IMG_0733.jpg"},
{"filename": "IMG_0769.JPG","full": "https://jvr.nyc3.cdn.digitaloceanspaces.com/images/mom/IMG_0769.JPG", "width": "4032", "height": "3024", "aspectRatio": "0.75", "src": "https://jvr.nyc3.cdn.digitaloceanspaces.com/images/mom/thumbs/IMG_0769.jpg"},
{"filename": "IMG_1261.jpg","full": "https://jvr.nyc3.cdn.digitaloceanspaces.com/images/mom/IMG_1261.jpg", "width": "3024", "height": "4032", "aspectRatio": "1.3333333333333333", "src": "https://jvr.nyc3.cdn.digitaloceanspaces.com/images/mom/thumbs/IMG_1261.jpg"},
{"filename": "IMG_1616.JPG","full": "https://jvr.nyc3.cdn.digitaloceanspaces.com/images/mom/IMG_1616.JPG", "width": "4032", "height": "3024", "aspectRatio": "0.75", "src": "https://jvr.nyc3.cdn.digitaloceanspaces.com/images/mom/thumbs/IMG_1616.jpg"},
{"filename": "IMG_20150804_134054924_HDR.jpg","full": "https://jvr.nyc3.cdn.digitaloceanspaces.com/images/mom/IMG_20150804_134054924_HDR.jpg", "width": "5248", "height": "2952", "aspectRatio": "0.5625", "src": "https://jvr.nyc3.cdn.digitaloceanspaces.com/images/mom/thumbs/IMG_20150804_134054924_HDR.jpg"},
{"filename": "IMG_2020.jpg","full": "https://jvr.nyc3.cdn.digitaloceanspaces.com/images/mom/IMG_2020.jpg", "width": "3024", "height": "4032", "aspectRatio": "1.3333333333333333", "src": "https://jvr.nyc3.cdn.digitaloceanspaces.com/images/mom/thumbs/IMG_2020.jpg"},
{"filename": "IMG_20220912_210338.jpg","full": "https://jvr.nyc3.cdn.digitaloceanspaces.com/images/mom/IMG_20220912_210338.jpg", "width": "555", "height": "694", "aspectRatio": "1.2504504504504506", "src": "https://jvr.nyc3.cdn.digitaloceanspaces.com/images/mom/thumbs/IMG_20220912_210338.jpg"},
{"filename": "IMG_2095.jpg","full": "https://jvr.nyc3.cdn.digitaloceanspaces.com/images/mom/IMG_2095.jpg", "width": "1231", "height": "1231", "aspectRatio": "1", "src": "https://jvr.nyc3.cdn.digitaloceanspaces.com/images/mom/thumbs/IMG_2095.jpg"},
{"filename": "IMG_2097.JPG","full": "https://jvr.nyc3.cdn.digitaloceanspaces.com/images/mom/IMG_2097.JPG", "width": "3264", "height": "2448", "aspectRatio": "0.75", "src": "https://jvr.nyc3.cdn.digitaloceanspaces.com/images/mom/thumbs/IMG_2097.jpg"},
{"filename": "IMG_2098.JPG","full": "https://jvr.nyc3.cdn.digitaloceanspaces.com/images/mom/IMG_2098.JPG", "width": "3264", "height": "2448", "aspectRatio": "0.75", "src": "https://jvr.nyc3.cdn.digitaloceanspaces.com/images/mom/thumbs/IMG_2098.jpg"},
{"filename": "IMG_2588.JPG","full": "https://jvr.nyc3.cdn.digitaloceanspaces.com/images/mom/IMG_2588.JPG", "width": "3264", "height": "2448", "aspectRatio": "0.75", "src": "https://jvr.nyc3.cdn.digitaloceanspaces.com/images/mom/thumbs/IMG_2588.jpg"},
{"filename": "IMG_2791.JPG","full": "https://jvr.nyc3.cdn.digitaloceanspaces.com/images/mom/IMG_2791.JPG", "width": "4032", "height": "3024", "aspectRatio": "0.75", "src": "https://jvr.nyc3.cdn.digitaloceanspaces.com/images/mom/thumbs/IMG_2791.jpg"},
{"filename": "IMG_2798.JPG","full": "https://jvr.nyc3.cdn.digitaloceanspaces.com/images/mom/IMG_2798.JPG", "width": "4032", "height": "3024", "aspectRatio": "0.75", "src": "https://jvr.nyc3.cdn.digitaloceanspaces.com/images/mom/thumbs/IMG_2798.jpg"},
{"filename": "IMG_2807.jpg","full": "https://jvr.nyc3.cdn.digitaloceanspaces.com/images/mom/IMG_2807.jpg", "width": "1242", "height": "962", "aspectRatio": "0.7745571658615137", "src": "https://jvr.nyc3.cdn.digitaloceanspaces.com/images/mom/thumbs/IMG_2807.jpg"},
{"filename": "IMG_3054.JPG","full": "https://jvr.nyc3.cdn.digitaloceanspaces.com/images/mom/IMG_3054.JPG", "width": "4032", "height": "3024", "aspectRatio": "0.75", "src": "https://jvr.nyc3.cdn.digitaloceanspaces.com/images/mom/thumbs/IMG_3054.jpg"},
{"filename": "IMG_3123.jpg","full": "https://jvr.nyc3.cdn.digitaloceanspaces.com/images/mom/IMG_3123.jpg", "width": "3024", "height": "3252", "aspectRatio": "1.0753968253968254", "src": "https://jvr.nyc3.cdn.digitaloceanspaces.com/images/mom/thumbs/IMG_3123.jpg"},
{"filename": "IMG_3292.JPG","full": "https://jvr.nyc3.cdn.digitaloceanspaces.com/images/mom/IMG_3292.JPG", "width": "3264", "height": "2448", "aspectRatio": "0.75", "src": "https://jvr.nyc3.cdn.digitaloceanspaces.com/images/mom/thumbs/IMG_3292.jpg"},
{"filename": "IMG_3383.jpg","full": "https://jvr.nyc3.cdn.digitaloceanspaces.com/images/mom/IMG_3383.jpg", "width": "3478", "height": "2582", "aspectRatio": "0.7423806785508913", "src": "https://jvr.nyc3.cdn.digitaloceanspaces.com/images/mom/thumbs/IMG_3383.jpg"},
{"filename": "IMG_3496.JPG","full": "https://jvr.nyc3.cdn.digitaloceanspaces.com/images/mom/IMG_3496.JPG", "width": "4032", "height": "3024", "aspectRatio": "0.75", "src": "https://jvr.nyc3.cdn.digitaloceanspaces.com/images/mom/thumbs/IMG_3496.jpg"},
{"filename": "IMG_3575.JPG","full": "https://jvr.nyc3.cdn.digitaloceanspaces.com/images/mom/IMG_3575.JPG", "width": "1536", "height": "1024", "aspectRatio": "0.6666666666666666", "src": "https://jvr.nyc3.cdn.digitaloceanspaces.com/images/mom/thumbs/IMG_3575.jpg"},
{"filename": "IMG_3621.jpg","full": "https://jvr.nyc3.cdn.digitaloceanspaces.com/images/mom/IMG_3621.jpg", "width": "3024", "height": "4032", "aspectRatio": "1.3333333333333333", "src": "https://jvr.nyc3.cdn.digitaloceanspaces.com/images/mom/thumbs/IMG_3621.jpg"},
{"filename": "IMG_3622.jpg","full": "https://jvr.nyc3.cdn.digitaloceanspaces.com/images/mom/IMG_3622.jpg", "width": "3024", "height": "4032", "aspectRatio": "1.3333333333333333", "src": "https://jvr.nyc3.cdn.digitaloceanspaces.com/images/mom/thumbs/IMG_3622.jpg"},
{"filename": "IMG_3793.jpg","full": "https://jvr.nyc3.cdn.digitaloceanspaces.com/images/mom/IMG_3793.jpg", "width": "2316", "height": "3088", "aspectRatio": "1.3333333333333333", "src": "https://jvr.nyc3.cdn.digitaloceanspaces.com/images/mom/thumbs/IMG_3793.jpg"},
{"filename": "IMG_3876.jpg","full": "https://jvr.nyc3.cdn.digitaloceanspaces.com/images/mom/IMG_3876.jpg", "width": "640", "height": "640", "aspectRatio": "1", "src": "https://jvr.nyc3.cdn.digitaloceanspaces.com/images/mom/thumbs/IMG_3876.jpg"},
{"filename": "IMG_3921.JPG","full": "https://jvr.nyc3.cdn.digitaloceanspaces.com/images/mom/IMG_3921.JPG", "width": "3264", "height": "2448", "aspectRatio": "0.75", "src": "https://jvr.nyc3.cdn.digitaloceanspaces.com/images/mom/thumbs/IMG_3921.jpg"},
{"filename": "IMG_3958.JPG","full": "https://jvr.nyc3.cdn.digitaloceanspaces.com/images/mom/IMG_3958.JPG", "width": "3264", "height": "2448", "aspectRatio": "0.75", "src": "https://jvr.nyc3.cdn.digitaloceanspaces.com/images/mom/thumbs/IMG_3958.jpg"},
{"filename": "IMG_4820.jpg","full": "https://jvr.nyc3.cdn.digitaloceanspaces.com/images/mom/IMG_4820.jpg", "width": "3024", "height": "4032", "aspectRatio": "1.3333333333333333", "src": "https://jvr.nyc3.cdn.digitaloceanspaces.com/images/mom/thumbs/IMG_4820.jpg"},
{"filename": "IMG_4822.jpg","full": "https://jvr.nyc3.cdn.digitaloceanspaces.com/images/mom/IMG_4822.jpg", "width": "3024", "height": "4032", "aspectRatio": "1.3333333333333333", "src": "https://jvr.nyc3.cdn.digitaloceanspaces.com/images/mom/thumbs/IMG_4822.jpg"},
{"filename": "IMG_5047.JPG","full": "https://jvr.nyc3.cdn.digitaloceanspaces.com/images/mom/IMG_5047.JPG", "width": "533", "height": "800", "aspectRatio": "1.5009380863039399", "src": "https://jvr.nyc3.cdn.digitaloceanspaces.com/images/mom/thumbs/IMG_5047.jpg"},
{"filename": "IMG_5096.JPG","full": "https://jvr.nyc3.cdn.digitaloceanspaces.com/images/mom/IMG_5096.JPG", "width": "720", "height": "529", "aspectRatio": "0.7347222222222223", "src": "https://jvr.nyc3.cdn.digitaloceanspaces.com/images/mom/thumbs/IMG_5096.jpg"},
{"filename": "IMG_5097.JPG","full": "https://jvr.nyc3.cdn.digitaloceanspaces.com/images/mom/IMG_5097.JPG", "width": "960", "height": "720", "aspectRatio": "0.75", "src": "https://jvr.nyc3.cdn.digitaloceanspaces.com/images/mom/thumbs/IMG_5097.jpg"},
{"filename": "IMG_5098.JPG","full": "https://jvr.nyc3.cdn.digitaloceanspaces.com/images/mom/IMG_5098.JPG", "width": "800", "height": "533", "aspectRatio": "0.66625", "src": "https://jvr.nyc3.cdn.digitaloceanspaces.com/images/mom/thumbs/IMG_5098.jpg"},
{"filename": "IMG_5099.JPG","full": "https://jvr.nyc3.cdn.digitaloceanspaces.com/images/mom/IMG_5099.JPG", "width": "800", "height": "533", "aspectRatio": "0.66625", "src": "https://jvr.nyc3.cdn.digitaloceanspaces.com/images/mom/thumbs/IMG_5099.jpg"},
{"filename": "IMG_5100.JPG","full": "https://jvr.nyc3.cdn.digitaloceanspaces.com/images/mom/IMG_5100.JPG", "width": "533", "height": "800", "aspectRatio": "1.5009380863039399", "src": "https://jvr.nyc3.cdn.digitaloceanspaces.com/images/mom/thumbs/IMG_5100.jpg"},
{"filename": "IMG_5102.JPG","full": "https://jvr.nyc3.cdn.digitaloceanspaces.com/images/mom/IMG_5102.JPG", "width": "800", "height": "533", "aspectRatio": "0.66625", "src": "https://jvr.nyc3.cdn.digitaloceanspaces.com/images/mom/thumbs/IMG_5102.jpg"},
{"filename": "IMG_5103.JPG","full": "https://jvr.nyc3.cdn.digitaloceanspaces.com/images/mom/IMG_5103.JPG", "width": "800", "height": "533", "aspectRatio": "0.66625", "src": "https://jvr.nyc3.cdn.digitaloceanspaces.com/images/mom/thumbs/IMG_5103.jpg"},
{"filename": "IMG_5104.JPG","full": "https://jvr.nyc3.cdn.digitaloceanspaces.com/images/mom/IMG_5104.JPG", "width": "533", "height": "800", "aspectRatio": "1.5009380863039399", "src": "https://jvr.nyc3.cdn.digitaloceanspaces.com/images/mom/thumbs/IMG_5104.jpg"},
{"filename": "IMG_5105.JPG","full": "https://jvr.nyc3.cdn.digitaloceanspaces.com/images/mom/IMG_5105.JPG", "width": "800", "height": "533", "aspectRatio": "0.66625", "src": "https://jvr.nyc3.cdn.digitaloceanspaces.com/images/mom/thumbs/IMG_5105.jpg"},
{"filename": "IMG_5106.JPG","full": "https://jvr.nyc3.cdn.digitaloceanspaces.com/images/mom/IMG_5106.JPG", "width": "533", "height": "800", "aspectRatio": "1.5009380863039399", "src": "https://jvr.nyc3.cdn.digitaloceanspaces.com/images/mom/thumbs/IMG_5106.jpg"},
{"filename": "IMG_5107.JPG","full": "https://jvr.nyc3.cdn.digitaloceanspaces.com/images/mom/IMG_5107.JPG", "width": "800", "height": "533", "aspectRatio": "0.66625", "src": "https://jvr.nyc3.cdn.digitaloceanspaces.com/images/mom/thumbs/IMG_5107.jpg"},
{"filename": "IMG_5108.JPG","full": "https://jvr.nyc3.cdn.digitaloceanspaces.com/images/mom/IMG_5108.JPG", "width": "533", "height": "800", "aspectRatio": "1.5009380863039399", "src": "https://jvr.nyc3.cdn.digitaloceanspaces.com/images/mom/thumbs/IMG_5108.jpg"},
{"filename": "IMG_5109.JPG","full": "https://jvr.nyc3.cdn.digitaloceanspaces.com/images/mom/IMG_5109.JPG", "width": "2048", "height": "1529", "aspectRatio": "0.74658203125", "src": "https://jvr.nyc3.cdn.digitaloceanspaces.com/images/mom/thumbs/IMG_5109.jpg"},
{"filename": "IMG_5110.JPG","full": "https://jvr.nyc3.cdn.digitaloceanspaces.com/images/mom/IMG_5110.JPG", "width": "2048", "height": "1363", "aspectRatio": "0.66552734375", "src": "https://jvr.nyc3.cdn.digitaloceanspaces.com/images/mom/thumbs/IMG_5110.jpg"},
{"filename": "IMG_5111.JPG","full": "https://jvr.nyc3.cdn.digitaloceanspaces.com/images/mom/IMG_5111.JPG", "width": "2048", "height": "1536", "aspectRatio": "0.75", "src": "https://jvr.nyc3.cdn.digitaloceanspaces.com/images/mom/thumbs/IMG_5111.jpg"},
{"filename": "IMG_5112.JPG","full": "https://jvr.nyc3.cdn.digitaloceanspaces.com/images/mom/IMG_5112.JPG", "width": "2048", "height": "1365", "aspectRatio": "0.66650390625", "src": "https://jvr.nyc3.cdn.digitaloceanspaces.com/images/mom/thumbs/IMG_5112.jpg"},
{"filename": "IMG_5113.JPG","full": "https://jvr.nyc3.cdn.digitaloceanspaces.com/images/mom/IMG_5113.JPG", "width": "1784", "height": "2048", "aspectRatio": "1.147982062780269", "src": "https://jvr.nyc3.cdn.digitaloceanspaces.com/images/mom/thumbs/IMG_5113.jpg"},
{"filename": "IMG_5114.JPG","full": "https://jvr.nyc3.cdn.digitaloceanspaces.com/images/mom/IMG_5114.JPG", "width": "2048", "height": "1365", "aspectRatio": "0.66650390625", "src": "https://jvr.nyc3.cdn.digitaloceanspaces.com/images/mom/thumbs/IMG_5114.jpg"},
{"filename": "IMG_5115.JPG","full": "https://jvr.nyc3.cdn.digitaloceanspaces.com/images/mom/IMG_5115.JPG", "width": "960", "height": "720", "aspectRatio": "0.75", "src": "https://jvr.nyc3.cdn.digitaloceanspaces.com/images/mom/thumbs/IMG_5115.jpg"},
{"filename": "IMG_5116.JPG","full": "https://jvr.nyc3.cdn.digitaloceanspaces.com/images/mom/IMG_5116.JPG", "width": "960", "height": "540", "aspectRatio": "0.5625", "src": "https://jvr.nyc3.cdn.digitaloceanspaces.com/images/mom/thumbs/IMG_5116.jpg"},
{"filename": "IMG_5117.JPG","full": "https://jvr.nyc3.cdn.digitaloceanspaces.com/images/mom/IMG_5117.JPG", "width": "1152", "height": "864", "aspectRatio": "0.75", "src": "https://jvr.nyc3.cdn.digitaloceanspaces.com/images/mom/thumbs/IMG_5117.jpg"},
{"filename": "IMG_5119.JPG","full": "https://jvr.nyc3.cdn.digitaloceanspaces.com/images/mom/IMG_5119.JPG", "width": "960", "height": "640", "aspectRatio": "0.6666666666666666", "src": "https://jvr.nyc3.cdn.digitaloceanspaces.com/images/mom/thumbs/IMG_5119.jpg"},
{"filename": "IMG_5120.JPG","full": "https://jvr.nyc3.cdn.digitaloceanspaces.com/images/mom/IMG_5120.JPG", "width": "960", "height": "717", "aspectRatio": "0.746875", "src": "https://jvr.nyc3.cdn.digitaloceanspaces.com/images/mom/thumbs/IMG_5120.jpg"},
{"filename": "IMG_5121.JPG","full": "https://jvr.nyc3.cdn.digitaloceanspaces.com/images/mom/IMG_5121.JPG", "width": "2048", "height": "1536", "aspectRatio": "0.75", "src": "https://jvr.nyc3.cdn.digitaloceanspaces.com/images/mom/thumbs/IMG_5121.jpg"},
{"filename": "IMG_5122.PNG","full": "https://jvr.nyc3.cdn.digitaloceanspaces.com/images/mom/IMG_5122.PNG", "width": "1242", "height": "2208", "aspectRatio": "1.7777777777777777", "src": "https://jvr.nyc3.cdn.digitaloceanspaces.com/images/mom/thumbs/IMG_5122.jpg"},
{"filename": "IMG_5123.JPG","full": "https://jvr.nyc3.cdn.digitaloceanspaces.com/images/mom/IMG_5123.JPG", "width": "960", "height": "720", "aspectRatio": "0.75", "src": "https://jvr.nyc3.cdn.digitaloceanspaces.com/images/mom/thumbs/IMG_5123.jpg"},
{"filename": "IMG_5124.JPG","full": "https://jvr.nyc3.cdn.digitaloceanspaces.com/images/mom/IMG_5124.JPG", "width": "960", "height": "720", "aspectRatio": "0.75", "src": "https://jvr.nyc3.cdn.digitaloceanspaces.com/images/mom/thumbs/IMG_5124.jpg"},
{"filename": "IMG_5125.JPG","full": "https://jvr.nyc3.cdn.digitaloceanspaces.com/images/mom/IMG_5125.JPG", "width": "960", "height": "720", "aspectRatio": "0.75", "src": "https://jvr.nyc3.cdn.digitaloceanspaces.com/images/mom/thumbs/IMG_5125.jpg"},
{"filename": "IMG_5126.JPG","full": "https://jvr.nyc3.cdn.digitaloceanspaces.com/images/mom/IMG_5126.JPG", "width": "960", "height": "720", "aspectRatio": "0.75", "src": "https://jvr.nyc3.cdn.digitaloceanspaces.com/images/mom/thumbs/IMG_5126.jpg"},
{"filename": "IMG_5127.JPG","full": "https://jvr.nyc3.cdn.digitaloceanspaces.com/images/mom/IMG_5127.JPG", "width": "960", "height": "720", "aspectRatio": "0.75", "src": "https://jvr.nyc3.cdn.digitaloceanspaces.com/images/mom/thumbs/IMG_5127.jpg"},
{"filename": "IMG_5128.JPG","full": "https://jvr.nyc3.cdn.digitaloceanspaces.com/images/mom/IMG_5128.JPG", "width": "960", "height": "720", "aspectRatio": "0.75", "src": "https://jvr.nyc3.cdn.digitaloceanspaces.com/images/mom/thumbs/IMG_5128.jpg"},
{"filename": "IMG_5129.JPG","full": "https://jvr.nyc3.cdn.digitaloceanspaces.com/images/mom/IMG_5129.JPG", "width": "960", "height": "720", "aspectRatio": "0.75", "src": "https://jvr.nyc3.cdn.digitaloceanspaces.com/images/mom/thumbs/IMG_5129.jpg"},
{"filename": "IMG_5130.JPG","full": "https://jvr.nyc3.cdn.digitaloceanspaces.com/images/mom/IMG_5130.JPG", "width": "960", "height": "720", "aspectRatio": "0.75", "src": "https://jvr.nyc3.cdn.digitaloceanspaces.com/images/mom/thumbs/IMG_5130.jpg"},
{"filename": "IMG_5131.JPG","full": "https://jvr.nyc3.cdn.digitaloceanspaces.com/images/mom/IMG_5131.JPG", "width": "720", "height": "720", "aspectRatio": "1", "src": "https://jvr.nyc3.cdn.digitaloceanspaces.com/images/mom/thumbs/IMG_5131.jpg"},
{"filename": "IMG_5134.JPG","full": "https://jvr.nyc3.cdn.digitaloceanspaces.com/images/mom/IMG_5134.JPG", "width": "720", "height": "540", "aspectRatio": "0.75", "src": "https://jvr.nyc3.cdn.digitaloceanspaces.com/images/mom/thumbs/IMG_5134.jpg"},
{"filename": "IMG_5144-2.jpg","full": "https://jvr.nyc3.cdn.digitaloceanspaces.com/images/mom/IMG_5144-2.jpg", "width": "1350", "height": "1960", "aspectRatio": "1.451851851851852", "src": "https://jvr.nyc3.cdn.digitaloceanspaces.com/images/mom/thumbs/IMG_5144-2.jpg"},
{"filename": "IMG_5146.jpg","full": "https://jvr.nyc3.cdn.digitaloceanspaces.com/images/mom/IMG_5146.jpg", "width": "1831", "height": "2562", "aspectRatio": "1.399235390496996", "src": "https://jvr.nyc3.cdn.digitaloceanspaces.com/images/mom/thumbs/IMG_5146.jpg"},
{"filename": "IMG_5147.jpg","full": "https://jvr.nyc3.cdn.digitaloceanspaces.com/images/mom/IMG_5147.jpg", "width": "1835", "height": "2896", "aspectRatio": "1.5782016348773842", "src": "https://jvr.nyc3.cdn.digitaloceanspaces.com/images/mom/thumbs/IMG_5147.jpg"},
{"filename": "IMG_5148.jpg","full": "https://jvr.nyc3.cdn.digitaloceanspaces.com/images/mom/IMG_5148.jpg", "width": "2423", "height": "1563", "aspectRatio": "0.6450680973999174", "src": "https://jvr.nyc3.cdn.digitaloceanspaces.com/images/mom/thumbs/IMG_5148.jpg"},
{"filename": "IMG_5149.jpg","full": "https://jvr.nyc3.cdn.digitaloceanspaces.com/images/mom/IMG_5149.jpg", "width": "2150", "height": "1446", "aspectRatio": "0.6725581395348837", "src": "https://jvr.nyc3.cdn.digitaloceanspaces.com/images/mom/thumbs/IMG_5149.jpg"},
{"filename": "IMG_5150.jpg","full": "https://jvr.nyc3.cdn.digitaloceanspaces.com/images/mom/IMG_5150.jpg", "width": "2065", "height": "3072", "aspectRatio": "1.4876513317191282", "src": "https://jvr.nyc3.cdn.digitaloceanspaces.com/images/mom/thumbs/IMG_5150.jpg"},
{"filename": "IMG_5155.jpg","full": "https://jvr.nyc3.cdn.digitaloceanspaces.com/images/mom/IMG_5155.jpg", "width": "3532", "height": "2402", "aspectRatio": "0.6800679501698754", "src": "https://jvr.nyc3.cdn.digitaloceanspaces.com/images/mom/thumbs/IMG_5155.jpg"},
{"filename": "IMG_5156.jpg","full": "https://jvr.nyc3.cdn.digitaloceanspaces.com/images/mom/IMG_5156.jpg", "width": "2758", "height": "1993", "aspectRatio": "0.7226250906453953", "src": "https://jvr.nyc3.cdn.digitaloceanspaces.com/images/mom/thumbs/IMG_5156.jpg"},
{"filename": "IMG_5583.JPG","full": "https://jvr.nyc3.cdn.digitaloceanspaces.com/images/mom/IMG_5583.JPG", "width": "1080", "height": "813", "aspectRatio": "0.7527777777777778", "src": "https://jvr.nyc3.cdn.digitaloceanspaces.com/images/mom/thumbs/IMG_5583.jpg"},
{"filename": "IMG_5584.JPG","full": "https://jvr.nyc3.cdn.digitaloceanspaces.com/images/mom/IMG_5584.JPG", "width": "1080", "height": "810", "aspectRatio": "0.75", "src": "https://jvr.nyc3.cdn.digitaloceanspaces.com/images/mom/thumbs/IMG_5584.jpg"},
{"filename": "IMG_7319.JPG","full": "https://jvr.nyc3.cdn.digitaloceanspaces.com/images/mom/IMG_7319.JPG", "width": "640", "height": "428", "aspectRatio": "0.66875", "src": "https://jvr.nyc3.cdn.digitaloceanspaces.com/images/mom/thumbs/IMG_7319.jpg"},
{"filename": "IMG_7325.JPG","full": "https://jvr.nyc3.cdn.digitaloceanspaces.com/images/mom/IMG_7325.JPG", "width": "640", "height": "428", "aspectRatio": "0.66875", "src": "https://jvr.nyc3.cdn.digitaloceanspaces.com/images/mom/thumbs/IMG_7325.jpg"},
{"filename": "IMG_7405.jpg","full": "https://jvr.nyc3.cdn.digitaloceanspaces.com/images/mom/IMG_7405.jpg", "width": "3024", "height": "4032", "aspectRatio": "1.3333333333333333", "src": "https://jvr.nyc3.cdn.digitaloceanspaces.com/images/mom/thumbs/IMG_7405.jpg"},
{"filename": "IMG_8177.jpg","full": "https://jvr.nyc3.cdn.digitaloceanspaces.com/images/mom/IMG_8177.jpg", "width": "3024", "height": "4032", "aspectRatio": "1.3333333333333333", "src": "https://jvr.nyc3.cdn.digitaloceanspaces.com/images/mom/thumbs/IMG_8177.jpg"},
{"filename": "IMG_8419.JPG","full": "https://jvr.nyc3.cdn.digitaloceanspaces.com/images/mom/IMG_8419.JPG", "width": "960", "height": "720", "aspectRatio": "0.75", "src": "https://jvr.nyc3.cdn.digitaloceanspaces.com/images/mom/thumbs/IMG_8419.jpg"},
{"filename": "IMG_9013.jpg","full": "https://jvr.nyc3.cdn.digitaloceanspaces.com/images/mom/IMG_9013.jpg", "width": "3024", "height": "4032", "aspectRatio": "1.3333333333333333", "src": "https://jvr.nyc3.cdn.digitaloceanspaces.com/images/mom/thumbs/IMG_9013.jpg"},
{"filename": "Image-1.jpg","full": "https://jvr.nyc3.cdn.digitaloceanspaces.com/images/mom/Image-1.jpg", "width": "1944", "height": "1944", "aspectRatio": "1", "src": "https://jvr.nyc3.cdn.digitaloceanspaces.com/images/mom/thumbs/Image-1.jpg"},
{"filename": "John-Kissing-Mom.jpg","full": "https://jvr.nyc3.cdn.digitaloceanspaces.com/images/mom/John-Kissing-Mom.jpg", "width": "2876", "height": "2048", "aspectRatio": "0.7121001390820584", "src": "https://jvr.nyc3.cdn.digitaloceanspaces.com/images/mom/thumbs/John-Kissing-Mom.jpg"},
{"filename": "Johns-3rd-Birthday.jpg","full": "https://jvr.nyc3.cdn.digitaloceanspaces.com/images/mom/Johns-3rd-Birthday.jpg", "width": "2596", "height": "1854", "aspectRatio": "0.714175654853621", "src": "https://jvr.nyc3.cdn.digitaloceanspaces.com/images/mom/thumbs/Johns-3rd-Birthday.jpg"},
{"filename": "Johns30PartyShow (103).jpg","full": "https://jvr.nyc3.cdn.digitaloceanspaces.com/images/mom/Johns30PartyShow (103).jpg", "width": "996", "height": "688", "aspectRatio": "0.6907630522088354", "src": "https://jvr.nyc3.cdn.digitaloceanspaces.com/images/mom/thumbs/Johns30PartyShow (103).jpg"},
{"filename": "Johns30PartyShow (17).jpg","full": "https://jvr.nyc3.cdn.digitaloceanspaces.com/images/mom/Johns30PartyShow (17).jpg", "width": "1196", "height": "780", "aspectRatio": "0.6521739130434783", "src": "https://jvr.nyc3.cdn.digitaloceanspaces.com/images/mom/thumbs/Johns30PartyShow (17).jpg"},
{"filename": "Johns30PartyShow (22).jpg","full": "https://jvr.nyc3.cdn.digitaloceanspaces.com/images/mom/Johns30PartyShow (22).jpg", "width": "1188", "height": "792", "aspectRatio": "0.6666666666666666", "src": "https://jvr.nyc3.cdn.digitaloceanspaces.com/images/mom/thumbs/Johns30PartyShow (22).jpg"},
{"filename": "Johns30PartyShow (23).JPG","full": "https://jvr.nyc3.cdn.digitaloceanspaces.com/images/mom/Johns30PartyShow (23).JPG", "width": "2000", "height": "1500", "aspectRatio": "0.75", "src": "https://jvr.nyc3.cdn.digitaloceanspaces.com/images/mom/thumbs/Johns30PartyShow (23).jpg"},
{"filename": "Johns30PartyShow (28).jpg","full": "https://jvr.nyc3.cdn.digitaloceanspaces.com/images/mom/Johns30PartyShow (28).jpg", "width": "784", "height": "1148", "aspectRatio": "1.4642857142857142", "src": "https://jvr.nyc3.cdn.digitaloceanspaces.com/images/mom/thumbs/Johns30PartyShow (28).jpg"},
{"filename": "Johns30PartyShow (34).jpg","full": "https://jvr.nyc3.cdn.digitaloceanspaces.com/images/mom/Johns30PartyShow (34).jpg", "width": "980", "height": "692", "aspectRatio": "0.7061224489795919", "src": "https://jvr.nyc3.cdn.digitaloceanspaces.com/images/mom/thumbs/Johns30PartyShow (34).jpg"},
{"filename": "Johns30PartyShow (38)2.jpg","full": "https://jvr.nyc3.cdn.digitaloceanspaces.com/images/mom/Johns30PartyShow (38)2.jpg", "width": "1183", "height": "769", "aspectRatio": "0.6500422654268808", "src": "https://jvr.nyc3.cdn.digitaloceanspaces.com/images/mom/thumbs/Johns30PartyShow (38)2.jpg"},
{"filename": "Johns30PartyShow (39).jpg","full": "https://jvr.nyc3.cdn.digitaloceanspaces.com/images/mom/Johns30PartyShow (39).jpg", "width": "680", "height": "960", "aspectRatio": "1.411764705882353", "src": "https://jvr.nyc3.cdn.digitaloceanspaces.com/images/mom/thumbs/Johns30PartyShow (39).jpg"},
{"filename": "Johns30PartyShow (55).jpg","full": "https://jvr.nyc3.cdn.digitaloceanspaces.com/images/mom/Johns30PartyShow (55).jpg", "width": "902", "height": "615", "aspectRatio": "0.6818181818181818", "src": "https://jvr.nyc3.cdn.digitaloceanspaces.com/images/mom/thumbs/Johns30PartyShow (55).jpg"},
{"filename": "Johns30PartyShow (61).jpg","full": "https://jvr.nyc3.cdn.digitaloceanspaces.com/images/mom/Johns30PartyShow (61).jpg", "width": "912", "height": "675", "aspectRatio": "0.7401315789473685", "src": "https://jvr.nyc3.cdn.digitaloceanspaces.com/images/mom/thumbs/Johns30PartyShow (61).jpg"},
{"filename": "Johns30PartyShow (68).jpg","full": "https://jvr.nyc3.cdn.digitaloceanspaces.com/images/mom/Johns30PartyShow (68).jpg", "width": "996", "height": "688", "aspectRatio": "0.6907630522088354", "src": "https://jvr.nyc3.cdn.digitaloceanspaces.com/images/mom/thumbs/Johns30PartyShow (68).jpg"},
{"filename": "Johns30PartyShow (7).jpg","full": "https://jvr.nyc3.cdn.digitaloceanspaces.com/images/mom/Johns30PartyShow (7).jpg", "width": "780", "height": "1184", "aspectRatio": "1.5179487179487179", "src": "https://jvr.nyc3.cdn.digitaloceanspaces.com/images/mom/thumbs/Johns30PartyShow (7).jpg"},
{"filename": "Johns30PartyShow (71).jpg","full": "https://jvr.nyc3.cdn.digitaloceanspaces.com/images/mom/Johns30PartyShow (71).jpg", "width": "1184", "height": "776", "aspectRatio": "0.6554054054054054", "src": "https://jvr.nyc3.cdn.digitaloceanspaces.com/images/mom/thumbs/Johns30PartyShow (71).jpg"},
{"filename": "Johns30PartyShow (72).JPG","full": "https://jvr.nyc3.cdn.digitaloceanspaces.com/images/mom/Johns30PartyShow (72).JPG", "width": "2000", "height": "1500", "aspectRatio": "0.75", "src": "https://jvr.nyc3.cdn.digitaloceanspaces.com/images/mom/thumbs/Johns30PartyShow (72).jpg"},
{"filename": "Johns30PartyShow (84).jpg","full": "https://jvr.nyc3.cdn.digitaloceanspaces.com/images/mom/Johns30PartyShow (84).jpg", "width": "940", "height": "684", "aspectRatio": "0.7276595744680852", "src": "https://jvr.nyc3.cdn.digitaloceanspaces.com/images/mom/thumbs/Johns30PartyShow (84).jpg"},
{"filename": "Johns30PartyShow (95).jpg","full": "https://jvr.nyc3.cdn.digitaloceanspaces.com/images/mom/Johns30PartyShow (95).jpg", "width": "944", "height": "664", "aspectRatio": "0.7033898305084746", "src": "https://jvr.nyc3.cdn.digitaloceanspaces.com/images/mom/thumbs/Johns30PartyShow (95).jpg"},
{"filename": "Mom-2.jpg","full": "https://jvr.nyc3.cdn.digitaloceanspaces.com/images/mom/Mom-2.jpg", "width": "654", "height": "939", "aspectRatio": "1.4357798165137614", "src": "https://jvr.nyc3.cdn.digitaloceanspaces.com/images/mom/thumbs/Mom-2.jpg"},
{"filename": "Mom-GmaSlote-Mark-John-Trainstation.jpg","full": "https://jvr.nyc3.cdn.digitaloceanspaces.com/images/mom/Mom-GmaSlote-Mark-John-Trainstation.jpg", "width": "3200", "height": "2286", "aspectRatio": "0.714375", "src": "https://jvr.nyc3.cdn.digitaloceanspaces.com/images/mom/thumbs/Mom-GmaSlote-Mark-John-Trainstation.jpg"},
{"filename": "Mom-Johns-11th-birthday-party-2.jpg","full": "https://jvr.nyc3.cdn.digitaloceanspaces.com/images/mom/Mom-Johns-11th-birthday-party-2.jpg", "width": "1516", "height": "1014", "aspectRatio": "0.6688654353562006", "src": "https://jvr.nyc3.cdn.digitaloceanspaces.com/images/mom/thumbs/Mom-Johns-11th-birthday-party-2.jpg"},
{"filename": "Mom-Johns-11th-birthday-party.jpg","full": "https://jvr.nyc3.cdn.digitaloceanspaces.com/images/mom/Mom-Johns-11th-birthday-party.jpg", "width": "1461", "height": "1025", "aspectRatio": "0.7015742642026009", "src": "https://jvr.nyc3.cdn.digitaloceanspaces.com/images/mom/thumbs/Mom-Johns-11th-birthday-party.jpg"},
{"filename": "Mom-Pioneer-Village-June-1986.jpg","full": "https://jvr.nyc3.cdn.digitaloceanspaces.com/images/mom/Mom-Pioneer-Village-June-1986.jpg", "width": "981", "height": "1034", "aspectRatio": "1.054026503567788", "src": "https://jvr.nyc3.cdn.digitaloceanspaces.com/images/mom/thumbs/Mom-Pioneer-Village-June-1986.jpg"},
{"filename": "Mom-Sachi-Kathy-2.jpg","full": "https://jvr.nyc3.cdn.digitaloceanspaces.com/images/mom/Mom-Sachi-Kathy-2.jpg", "width": "1584", "height": "1002", "aspectRatio": "0.6325757575757576", "src": "https://jvr.nyc3.cdn.digitaloceanspaces.com/images/mom/thumbs/Mom-Sachi-Kathy-2.jpg"},
{"filename": "Mom-Sachi-Kathy.jpg","full": "https://jvr.nyc3.cdn.digitaloceanspaces.com/images/mom/Mom-Sachi-Kathy.jpg", "width": "792", "height": "759", "aspectRatio": "0.9583333333333334", "src": "https://jvr.nyc3.cdn.digitaloceanspaces.com/images/mom/thumbs/Mom-Sachi-Kathy.jpg"},
{"filename": "Mom-and-Dad--40thAnniversary--Omaha.jpg","full": "https://jvr.nyc3.cdn.digitaloceanspaces.com/images/mom/Mom-and-Dad--40thAnniversary--Omaha.jpg", "width": "1952", "height": "3264", "aspectRatio": "1.6721311475409837", "src": "https://jvr.nyc3.cdn.digitaloceanspaces.com/images/mom/thumbs/Mom-and-Dad--40thAnniversary--Omaha.jpg"},
{"filename": "Mom-and-Dad-1.jpg","full": "https://jvr.nyc3.cdn.digitaloceanspaces.com/images/mom/Mom-and-Dad-1.jpg", "width": "979", "height": "983", "aspectRatio": "1.0040858018386107", "src": "https://jvr.nyc3.cdn.digitaloceanspaces.com/images/mom/thumbs/Mom-and-Dad-1.jpg"},
{"filename": "Mom-and-Dad-ChurchPhoto.jpg","full": "https://jvr.nyc3.cdn.digitaloceanspaces.com/images/mom/Mom-and-Dad-ChurchPhoto.jpg", "width": "424", "height": "586", "aspectRatio": "1.3820754716981132", "src": "https://jvr.nyc3.cdn.digitaloceanspaces.com/images/mom/thumbs/Mom-and-Dad-ChurchPhoto.jpg"},
{"filename": "Mom-and-Dad-wedding-1.jpg","full": "https://jvr.nyc3.cdn.digitaloceanspaces.com/images/mom/Mom-and-Dad-wedding-1.jpg", "width": "2279", "height": "2861", "aspectRatio": "1.2553751645458535", "src": "https://jvr.nyc3.cdn.digitaloceanspaces.com/images/mom/thumbs/Mom-and-Dad-wedding-1.jpg"},
{"filename": "Mom-and-Dad-wedding.jpg","full": "https://jvr.nyc3.cdn.digitaloceanspaces.com/images/mom/Mom-and-Dad-wedding.jpg", "width": "921", "height": "1366", "aspectRatio": "1.483170466883822", "src": "https://jvr.nyc3.cdn.digitaloceanspaces.com/images/mom/thumbs/Mom-and-Dad-wedding.jpg"},
{"filename": "Mom-and-Dad-with-Haases-Leths-Wickhams-1987-07.jpg","full": "https://jvr.nyc3.cdn.digitaloceanspaces.com/images/mom/Mom-and-Dad-with-Haases-Leths-Wickhams-1987-07.jpg", "width": "1507", "height": "1024", "aspectRatio": "0.6794956867949569", "src": "https://jvr.nyc3.cdn.digitaloceanspaces.com/images/mom/thumbs/Mom-and-Dad-with-Haases-Leths-Wickhams-1987-07.jpg"},
{"filename": "Mom-and-Dad.jpg","full": "https://jvr.nyc3.cdn.digitaloceanspaces.com/images/mom/Mom-and-Dad.jpg", "width": "854", "height": "774", "aspectRatio": "0.9063231850117096", "src": "https://jvr.nyc3.cdn.digitaloceanspaces.com/images/mom/thumbs/Mom-and-Dad.jpg"},
{"filename": "Mom-and-John-Newborn-noadjust.jpg","full": "https://jvr.nyc3.cdn.digitaloceanspaces.com/images/mom/Mom-and-John-Newborn-noadjust.jpg", "width": "2890", "height": "2076", "aspectRatio": "0.7183391003460208", "src": "https://jvr.nyc3.cdn.digitaloceanspaces.com/images/mom/thumbs/Mom-and-John-Newborn-noadjust.jpg"},
{"filename": "Mom-and-John.jpg","full": "https://jvr.nyc3.cdn.digitaloceanspaces.com/images/mom/Mom-and-John.jpg", "width": "1376", "height": "991", "aspectRatio": "0.720203488372093", "src": "https://jvr.nyc3.cdn.digitaloceanspaces.com/images/mom/thumbs/Mom-and-John.jpg"},
{"filename": "Mom-and-Vika-2006.jpg","full": "https://jvr.nyc3.cdn.digitaloceanspaces.com/images/mom/Mom-and-Vika-2006.jpg", "width": "1167", "height": "1721", "aspectRatio": "1.4747215081405314", "src": "https://jvr.nyc3.cdn.digitaloceanspaces.com/images/mom/thumbs/Mom-and-Vika-2006.jpg"},
{"filename": "Mom-and-dad-3.jpg","full": "https://jvr.nyc3.cdn.digitaloceanspaces.com/images/mom/Mom-and-dad-3.jpg", "width": "1393", "height": "998", "aspectRatio": "0.7164393395549175", "src": "https://jvr.nyc3.cdn.digitaloceanspaces.com/images/mom/thumbs/Mom-and-dad-3.jpg"},
{"filename": "Mom-and-dad-4.jpg","full": "https://jvr.nyc3.cdn.digitaloceanspaces.com/images/mom/Mom-and-dad-4.jpg", "width": "1158", "height": "1736", "aspectRatio": "1.4991364421416236", "src": "https://jvr.nyc3.cdn.digitaloceanspaces.com/images/mom/thumbs/Mom-and-dad-4.jpg"},
{"filename": "Mom-and-newborn-John.jpg","full": "https://jvr.nyc3.cdn.digitaloceanspaces.com/images/mom/Mom-and-newborn-John.jpg", "width": "1385", "height": "991", "aspectRatio": "0.7155234657039711", "src": "https://jvr.nyc3.cdn.digitaloceanspaces.com/images/mom/thumbs/Mom-and-newborn-John.jpg"},
{"filename": "Mom-on-Johns_1stSchoolDay.jpg","full": "https://jvr.nyc3.cdn.digitaloceanspaces.com/images/mom/Mom-on-Johns_1stSchoolDay.jpg", "width": "2464", "height": "1760", "aspectRatio": "0.7142857142857143", "src": "https://jvr.nyc3.cdn.digitaloceanspaces.com/images/mom/thumbs/Mom-on-Johns_1stSchoolDay.jpg"},
{"filename": "Mom-pregnant-with-John-2.jpg","full": "https://jvr.nyc3.cdn.digitaloceanspaces.com/images/mom/Mom-pregnant-with-John-2.jpg", "width": "953", "height": "1012", "aspectRatio": "1.061909758656873", "src": "https://jvr.nyc3.cdn.digitaloceanspaces.com/images/mom/thumbs/Mom-pregnant-with-John-2.jpg"},
{"filename": "Mom-pregnant-with-John.jpg","full": "https://jvr.nyc3.cdn.digitaloceanspaces.com/images/mom/Mom-pregnant-with-John.jpg", "width": "1001", "height": "952", "aspectRatio": "0.951048951048951", "src": "https://jvr.nyc3.cdn.digitaloceanspaces.com/images/mom/thumbs/Mom-pregnant-with-John.jpg"},
{"filename": "Mom.jpg","full": "https://jvr.nyc3.cdn.digitaloceanspaces.com/images/mom/Mom.jpg", "width": "905", "height": "1348", "aspectRatio": "1.4895027624309392", "src": "https://jvr.nyc3.cdn.digitaloceanspaces.com/images/mom/thumbs/Mom.jpg"},
{"filename": "P1010024.JPG","full": "https://jvr.nyc3.cdn.digitaloceanspaces.com/images/mom/P1010024.JPG", "width": "4000", "height": "3000", "aspectRatio": "0.75", "src": "https://jvr.nyc3.cdn.digitaloceanspaces.com/images/mom/thumbs/P1010024.jpg"},
{"filename": "PART_1526698219843_IMG950217.jpg","full": "https://jvr.nyc3.cdn.digitaloceanspaces.com/images/mom/PART_1526698219843_IMG950217.jpg", "width": "809", "height": "790", "aspectRatio": "0.9765142150803461", "src": "https://jvr.nyc3.cdn.digitaloceanspaces.com/images/mom/thumbs/PART_1526698219843_IMG950217.jpg"},
{"filename": "Rick-Sachi-Albert-Kathy-Mom-Dad-2.jpg","full": "https://jvr.nyc3.cdn.digitaloceanspaces.com/images/mom/Rick-Sachi-Albert-Kathy-Mom-Dad-2.jpg", "width": "1565", "height": "1072", "aspectRatio": "0.6849840255591054", "src": "https://jvr.nyc3.cdn.digitaloceanspaces.com/images/mom/thumbs/Rick-Sachi-Albert-Kathy-Mom-Dad-2.jpg"},
{"filename": "Rick-Sachi-Albert-Kathy-Mom-Dad.jpg","full": "https://jvr.nyc3.cdn.digitaloceanspaces.com/images/mom/Rick-Sachi-Albert-Kathy-Mom-Dad.jpg", "width": "1619", "height": "1141", "aspectRatio": "0.7047560222359481", "src": "https://jvr.nyc3.cdn.digitaloceanspaces.com/images/mom/thumbs/Rick-Sachi-Albert-Kathy-Mom-Dad.jpg"},
{"filename": "Scan.jpg","full": "https://jvr.nyc3.cdn.digitaloceanspaces.com/images/mom/Scan.jpg", "width": "654", "height": "939", "aspectRatio": "1.4357798165137614", "src": "https://jvr.nyc3.cdn.digitaloceanspaces.com/images/mom/thumbs/Scan.jpg"},
{"filename": "Scan10172013182434_001.jpg","full": "https://jvr.nyc3.cdn.digitaloceanspaces.com/images/mom/Scan10172013182434_001.jpg", "width": "1763", "height": "1156", "aspectRatio": "0.655700510493477", "src": "https://jvr.nyc3.cdn.digitaloceanspaces.com/images/mom/thumbs/Scan10172013182434_001.jpg"},
{"filename": "dad-mark-john-mom-cosmo-michelle-in-hastings.jpg","full": "https://jvr.nyc3.cdn.digitaloceanspaces.com/images/mom/dad-mark-john-mom-cosmo-michelle-in-hastings.jpg", "width": "1732", "height": "1143", "aspectRatio": "0.6599307159353349", "src": "https://jvr.nyc3.cdn.digitaloceanspaces.com/images/mom/thumbs/dad-mark-john-mom-cosmo-michelle-in-hastings.jpg"},
{"filename": "dad-mom-2010-11-25.jpg","full": "https://jvr.nyc3.cdn.digitaloceanspaces.com/images/mom/dad-mom-2010-11-25.jpg", "width": "1730", "height": "1135", "aspectRatio": "0.6560693641618497", "src": "https://jvr.nyc3.cdn.digitaloceanspaces.com/images/mom/thumbs/dad-mom-2010-11-25.jpg"},
{"filename": "dad-mom-rojean-tom-2010-05-10.jpg","full": "https://jvr.nyc3.cdn.digitaloceanspaces.com/images/mom/dad-mom-rojean-tom-2010-05-10.jpg", "width": "1753", "height": "1154", "aspectRatio": "0.6583000570450656", "src": "https://jvr.nyc3.cdn.digitaloceanspaces.com/images/mom/thumbs/dad-mom-rojean-tom-2010-05-10.jpg"},
{"filename": "dana-mark-john-mom-dad-2010-12-12.jpg","full": "https://jvr.nyc3.cdn.digitaloceanspaces.com/images/mom/dana-mark-john-mom-dad-2010-12-12.jpg", "width": "1744", "height": "1153", "aspectRatio": "0.6611238532110092", "src": "https://jvr.nyc3.cdn.digitaloceanspaces.com/images/mom/thumbs/dana-mark-john-mom-dad-2010-12-12.jpg"},
{"filename": "danielle-cassie-john-janessa-mom-2010-06-20.jpg","full": "https://jvr.nyc3.cdn.digitaloceanspaces.com/images/mom/danielle-cassie-john-janessa-mom-2010-06-20.jpg", "width": "1745", "height": "1164", "aspectRatio": "0.6670487106017192", "src": "https://jvr.nyc3.cdn.digitaloceanspaces.com/images/mom/thumbs/danielle-cassie-john-janessa-mom-2010-06-20.jpg"},
{"filename": "deanna-12-mom-3-rojean-14.jpg","full": "https://jvr.nyc3.cdn.digitaloceanspaces.com/images/mom/deanna-12-mom-3-rojean-14.jpg", "width": "2792", "height": "2204", "aspectRatio": "0.7893982808022922", "src": "https://jvr.nyc3.cdn.digitaloceanspaces.com/images/mom/thumbs/deanna-12-mom-3-rojean-14.jpg"},
{"filename": "deanna-baby-mom-rojean.jpg","full": "https://jvr.nyc3.cdn.digitaloceanspaces.com/images/mom/deanna-baby-mom-rojean.jpg", "width": "1127", "height": "1640", "aspectRatio": "1.4551907719609583", "src": "https://jvr.nyc3.cdn.digitaloceanspaces.com/images/mom/thumbs/deanna-baby-mom-rojean.jpg"},
{"filename": "deanna-rojean-mom-2009.jpg","full": "https://jvr.nyc3.cdn.digitaloceanspaces.com/images/mom/deanna-rojean-mom-2009.jpg", "width": "1660", "height": "1086", "aspectRatio": "0.6542168674698795", "src": "https://jvr.nyc3.cdn.digitaloceanspaces.com/images/mom/thumbs/deanna-rojean-mom-2009.jpg"},
{"filename": "erica-and-mom-1987.jpg","full": "https://jvr.nyc3.cdn.digitaloceanspaces.com/images/mom/erica-and-mom-1987.jpg", "width": "991", "height": "1503", "aspectRatio": "1.5166498486377396", "src": "https://jvr.nyc3.cdn.digitaloceanspaces.com/images/mom/thumbs/erica-and-mom-1987.jpg"},
{"filename": "grandpa-grandma-slote-mom-1960-11.jpg","full": "https://jvr.nyc3.cdn.digitaloceanspaces.com/images/mom/grandpa-grandma-slote-mom-1960-11.jpg", "width": "1031", "height": "1036", "aspectRatio": "1.0048496605237633", "src": "https://jvr.nyc3.cdn.digitaloceanspaces.com/images/mom/thumbs/grandpa-grandma-slote-mom-1960-11.jpg"},
{"filename": "john-grandma-ritterbush-mark-dad-mom-cosmo-in-hastings.jpg","full": "https://jvr.nyc3.cdn.digitaloceanspaces.com/images/mom/john-grandma-ritterbush-mark-dad-mom-cosmo-in-hastings.jpg", "width": "1736", "height": "1138", "aspectRatio": "0.6555299539170507", "src": "https://jvr.nyc3.cdn.digitaloceanspaces.com/images/mom/thumbs/john-grandma-ritterbush-mark-dad-mom-cosmo-in-hastings.jpg"},
{"filename": "john-mark-dad-mom-cosmo-christmas-hastings.jpg","full": "https://jvr.nyc3.cdn.digitaloceanspaces.com/images/mom/john-mark-dad-mom-cosmo-christmas-hastings.jpg", "width": "1700", "height": "1078", "aspectRatio": "0.6341176470588236", "src": "https://jvr.nyc3.cdn.digitaloceanspaces.com/images/mom/thumbs/john-mark-dad-mom-cosmo-christmas-hastings.jpg"},
{"filename": "john-mark-mom-at-grandma-demoss.jpg","full": "https://jvr.nyc3.cdn.digitaloceanspaces.com/images/mom/john-mark-mom-at-grandma-demoss.jpg", "width": "1504", "height": "990", "aspectRatio": "0.6582446808510638", "src": "https://jvr.nyc3.cdn.digitaloceanspaces.com/images/mom/thumbs/john-mark-mom-at-grandma-demoss.jpg"},
{"filename": "john-mom-2010-06-20.jpg","full": "https://jvr.nyc3.cdn.digitaloceanspaces.com/images/mom/john-mom-2010-06-20.jpg", "width": "1132", "height": "1559", "aspectRatio": "1.377208480565371", "src": "https://jvr.nyc3.cdn.digitaloceanspaces.com/images/mom/thumbs/john-mom-2010-06-20.jpg"},
{"filename": "mom-and-john-birthday.jpg","full": "https://jvr.nyc3.cdn.digitaloceanspaces.com/images/mom/mom-and-john-birthday.jpg", "width": "1488", "height": "990", "aspectRatio": "0.6653225806451613", "src": "https://jvr.nyc3.cdn.digitaloceanspaces.com/images/mom/thumbs/mom-and-john-birthday.jpg"},
{"filename": "mom-and-lori.jpg","full": "https://jvr.nyc3.cdn.digitaloceanspaces.com/images/mom/mom-and-lori.jpg", "width": "1750", "height": "1155", "aspectRatio": "0.66", "src": "https://jvr.nyc3.cdn.digitaloceanspaces.com/images/mom/thumbs/mom-and-lori.jpg"},
{"filename": "mom-and-mark-at-grandma-slotes.jpg","full": "https://jvr.nyc3.cdn.digitaloceanspaces.com/images/mom/mom-and-mark-at-grandma-slotes.jpg", "width": "1722", "height": "1128", "aspectRatio": "0.6550522648083623", "src": "https://jvr.nyc3.cdn.digitaloceanspaces.com/images/mom/thumbs/mom-and-mark-at-grandma-slotes.jpg"},
{"filename": "mom-at-grandma-slotes.jpg","full": "https://jvr.nyc3.cdn.digitaloceanspaces.com/images/mom/mom-at-grandma-slotes.jpg", "width": "1731", "height": "1136", "aspectRatio": "0.6562680531484691", "src": "https://jvr.nyc3.cdn.digitaloceanspaces.com/images/mom/thumbs/mom-at-grandma-slotes.jpg"},
{"filename": "mom-bowling-2001.jpg","full": "https://jvr.nyc3.cdn.digitaloceanspaces.com/images/mom/mom-bowling-2001.jpg", "width": "1028", "height": "697", "aspectRatio": "0.6780155642023347", "src": "https://jvr.nyc3.cdn.digitaloceanspaces.com/images/mom/thumbs/mom-bowling-2001.jpg"},
{"filename": "mom-bowling-2003.jpg","full": "https://jvr.nyc3.cdn.digitaloceanspaces.com/images/mom/mom-bowling-2003.jpg", "width": "977", "height": "644", "aspectRatio": "0.6591606960081884", "src": "https://jvr.nyc3.cdn.digitaloceanspaces.com/images/mom/thumbs/mom-bowling-2003.jpg"},
{"filename": "mom-bowling-2005.jpg","full": "https://jvr.nyc3.cdn.digitaloceanspaces.com/images/mom/mom-bowling-2005.jpg", "width": "942", "height": "653", "aspectRatio": "0.6932059447983014", "src": "https://jvr.nyc3.cdn.digitaloceanspaces.com/images/mom/thumbs/mom-bowling-2005.jpg"},
{"filename": "mom-bowling-2006.jpg","full": "https://jvr.nyc3.cdn.digitaloceanspaces.com/images/mom/mom-bowling-2006.jpg", "width": "1016", "height": "725", "aspectRatio": "0.7135826771653543", "src": "https://jvr.nyc3.cdn.digitaloceanspaces.com/images/mom/thumbs/mom-bowling-2006.jpg"},
{"filename": "mom-bowling-2007.jpg","full": "https://jvr.nyc3.cdn.digitaloceanspaces.com/images/mom/mom-bowling-2007.jpg", "width": "1018", "height": "702", "aspectRatio": "0.6895874263261297", "src": "https://jvr.nyc3.cdn.digitaloceanspaces.com/images/mom/thumbs/mom-bowling-2007.jpg"},
{"filename": "mom-dad-franklin-1987.jpg","full": "https://jvr.nyc3.cdn.digitaloceanspaces.com/images/mom/mom-dad-franklin-1987.jpg", "width": "1012", "height": "1517", "aspectRatio": "1.4990118577075098", "src": "https://jvr.nyc3.cdn.digitaloceanspaces.com/images/mom/thumbs/mom-dad-franklin-1987.jpg"},
{"filename": "mom-dad-rojean-tom-steve-michelle-emily-2010-06-12.jpg","full": "https://jvr.nyc3.cdn.digitaloceanspaces.com/images/mom/mom-dad-rojean-tom-steve-michelle-emily-2010-06-12.jpg", "width": "1660", "height": "1058", "aspectRatio": "0.6373493975903615", "src": "https://jvr.nyc3.cdn.digitaloceanspaces.com/images/mom/thumbs/mom-dad-rojean-tom-steve-michelle-emily-2010-06-12.jpg"},
{"filename": "mom-deanna-rojean-2009.jpg","full": "https://jvr.nyc3.cdn.digitaloceanspaces.com/images/mom/mom-deanna-rojean-2009.jpg", "width": "1753", "height": "1133", "aspectRatio": "0.6463205932686823", "src": "https://jvr.nyc3.cdn.digitaloceanspaces.com/images/mom/thumbs/mom-deanna-rojean-2009.jpg"},
{"filename": "mom-deanna-rojean-2010-05-08.jpg","full": "https://jvr.nyc3.cdn.digitaloceanspaces.com/images/mom/mom-deanna-rojean-2010-05-08.jpg", "width": "1690", "height": "1123", "aspectRatio": "0.6644970414201183", "src": "https://jvr.nyc3.cdn.digitaloceanspaces.com/images/mom/thumbs/mom-deanna-rojean-2010-05-08.jpg"},
{"filename": "mom-rojean-michelle-2010.jpg","full": "https://jvr.nyc3.cdn.digitaloceanspaces.com/images/mom/mom-rojean-michelle-2010.jpg", "width": "1728", "height": "1154", "aspectRatio": "0.6678240740740741", "src": "https://jvr.nyc3.cdn.digitaloceanspaces.com/images/mom/thumbs/mom-rojean-michelle-2010.jpg"},
{"filename": "mom-sheri-2010-06-17.jpg","full": "https://jvr.nyc3.cdn.digitaloceanspaces.com/images/mom/mom-sheri-2010-06-17.jpg", "width": "1758", "height": "1158", "aspectRatio": "0.658703071672355", "src": "https://jvr.nyc3.cdn.digitaloceanspaces.com/images/mom/thumbs/mom-sheri-2010-06-17.jpg"},
{"filename": "p1000131.JPG","full": "https://jvr.nyc3.cdn.digitaloceanspaces.com/images/mom/p1000131.JPG", "width": "2560", "height": "1920", "aspectRatio": "0.75", "src": "https://jvr.nyc3.cdn.digitaloceanspaces.com/images/mom/thumbs/p1000131.jpg"},
{"filename": "rojean-deanna-mom-2010-11-25.jpg","full": "https://jvr.nyc3.cdn.digitaloceanspaces.com/images/mom/rojean-deanna-mom-2010-11-25.jpg", "width": "1727", "height": "1133", "aspectRatio": "0.6560509554140127", "src": "https://jvr.nyc3.cdn.digitaloceanspaces.com/images/mom/thumbs/rojean-deanna-mom-2010-11-25.jpg"},
{"filename": "rojean-deanna-mom.jpg","full": "https://jvr.nyc3.cdn.digitaloceanspaces.com/images/mom/rojean-deanna-mom.jpg", "width": "1566", "height": "1026", "aspectRatio": "0.6551724137931034", "src": "https://jvr.nyc3.cdn.digitaloceanspaces.com/images/mom/thumbs/rojean-deanna-mom.jpg"},
{"filename": "rojean-mom-deanna.jpg","full": "https://jvr.nyc3.cdn.digitaloceanspaces.com/images/mom/rojean-mom-deanna.jpg", "width": "1148", "height": "1683", "aspectRatio": "1.46602787456446", "src": "https://jvr.nyc3.cdn.digitaloceanspaces.com/images/mom/thumbs/rojean-mom-deanna.jpg"},
{"filename": "skipbo-john-mom-grandma-ritterbush.jpg","full": "https://jvr.nyc3.cdn.digitaloceanspaces.com/images/mom/skipbo-john-mom-grandma-ritterbush.jpg", "width": "1487", "height": "982", "aspectRatio": "0.660390047074647", "src": "https://jvr.nyc3.cdn.digitaloceanspaces.com/images/mom/thumbs/skipbo-john-mom-grandma-ritterbush.jpg"}
]
